opensesame_extensions/sigmund/__init__.py
opensesame_extensions/sigmund/sigmund/__init__.py
opensesame_extensions/sigmund/sigmund/chat_widget.py
opensesame_extensions/sigmund/sigmund/example_item_scripts.py
opensesame_extensions/sigmund/sigmund/opensesame_workspace.py
opensesame_extensions/sigmund/sigmund/sigmund.png
opensesame_extensions/sigmund/sigmund/sigmund.py
opensesame_extensions/sigmund/sigmund/sigmund_widget.py
sigmund_qtwidget/__init__.py
sigmund_qtwidget/chat_browser.py
sigmund_qtwidget/chat_widget.py
sigmund_qtwidget/diff_dialog.py
sigmund_qtwidget/sigmund-full.png
sigmund_qtwidget/sigmund_dock_widget.py
sigmund_qtwidget/sigmund_widget.py
sigmund_qtwidget/stylesheet-dark.css
sigmund_qtwidget/stylesheet-light.css
sigmund_qtwidget/stylesheet.py
sigmund_qtwidget/websocket_server.py
opensesame_extension_sigmund-1.0.0.dist-info/METADATA
opensesame_extension_sigmund-1.0.0.dist-info/WHEEL
opensesame_extension_sigmund-1.0.0.dist-info/licenses/COPYING
opensesame_extension_sigmund-1.0.0.dist-info/RECORD
