Metadata-Version: 2.4
Name: opensesame-extension-sigmund
Version: 1.0.0
Summary: SigmundAI copilot extension for OpenSesame and Sigmund Analyst
License: COPYING
License-File: COPYING
Author: Sebastiaan Mathôt
Author-email: s.mathot@cogsci.nl
Classifier: License :: Other/Proprietary License
Classifier: Programming Language :: Python :: 2
Classifier: Programming Language :: Python :: 2.7
Classifier: Programming Language :: Python :: 3
Classifier: Programming Language :: Python :: 3.4
Classifier: Programming Language :: Python :: 3.5
Classifier: Programming Language :: Python :: 3.6
Classifier: Programming Language :: Python :: 3.7
Classifier: Programming Language :: Python :: 3.8
Classifier: Programming Language :: Python :: 3.9
Classifier: Programming Language :: Python :: 3.10
Classifier: Programming Language :: Python :: 3.11
Classifier: Programming Language :: Python :: 3.12
Classifier: Programming Language :: Python :: 3.13
Classifier: Programming Language :: Python :: 3.14
Requires-Dist: websockets (>=10)
Project-URL: Homepage, https://osdoc.cogsci.nl
Project-URL: Repository, https://github.com/open-cogsci/opensesame-extension-sigmund
